ether_wallet/__init__.py
ether_wallet/erc20.abi
ether_wallet/exceptions.py
ether_wallet/globals.py
ether_wallet/types.py
ether_wallet/utils.py
ether_wallet/wallet.py
ether_wallet-1.0.0.dist-info/LICENSE
ether_wallet-1.0.0.dist-info/METADATA
ether_wallet-1.0.0.dist-info/WHEEL
ether_wallet-1.0.0.dist-info/top_level.txt
ether_wallet-1.0.0.dist-info/RECORD
