Metadata-Version: 2.1
Name: ether-wallet
Version: 1.0.0
Summary: The package, containing wrapper over EVM operations for interacting through Wallet entities.
Home-page: https://github.com/blnkoff/ether-wallet
Author: Alexey
Author-email: Alexey <abelenkov2006@gmail.com>
Project-URL: source, https://github.com/blnkoff/ether-wallet
Keywords: ethereum wallet,ether wallet
Classifier: Development Status :: 5 - Production/Stable
Classifier: Intended Audience :: Developers
Classifier: Topic :: Software Development :: Build Tools
Classifier: Programming Language :: Python :: 3.11
Classifier: Programming Language :: Python :: 3 :: Only
Classifier: License :: OSI Approved :: Apache Software License
Classifier: Operating System :: Microsoft :: Windows
Classifier: Operating System :: MacOS
Requires-Python: >=3.11
License-File: LICENSE
